geospock_cli/__init__.py
geospock_cli/auth.py
geospock_cli/config_reader.py
geospock_cli/exceptions.py
geospock_cli/geospockcli.py
geospock_cli/message_sender.py
geospock_cli/messages.json
geospock_cli/graphql_templates/getCommand.graphql
geospock_cli/graphql_templates/getCommands.graphql
geospock_cli-3.0.6.dist-info/LICENSE
geospock_cli-3.0.6.dist-info/METADATA
geospock_cli-3.0.6.dist-info/WHEEL
geospock_cli-3.0.6.dist-info/entry_points.txt
geospock_cli-3.0.6.dist-info/top_level.txt
geospock_cli-3.0.6.dist-info/RECORD
