Metadata-Version: 2.1
Name: geospock-cli
Version: 3.0.6
Summary: GeoSpock CLI
Home-page: http://geospock.com/
Author: GeoSpock Ltd
Author-email: cli-development@geospock.com
License: MIT
Platform: UNKNOWN
Classifier: Development Status :: 5 - Production/Stable
Classifier: Environment :: Console
Classifier: License :: OSI Approved :: MIT License
Classifier: Programming Language :: Python :: 3
Requires-Python: >=3
Requires-Dist: Click
Requires-Dist: boto3
Requires-Dist: keyring (<=22.0.1)
Requires-Dist: tenacity (<=6.3.1)
